{
  "main": {
    "id": "edd4e88de4ede76c",
    "type": "split",
    "children": [
      {
        "id": "47431217505b11ff",
        "type": "tabs",
        "children": [
          {
            "id": "5195e31f07bf8a86",
            "type": "leaf",
            "state": {
              "type": "markdown",
              "state": {
                "file": "content/notas/2025/05/07/entrada/Jala_University-Engenharia_de_Software.md",
                "mode": "source",
                "source": false
              },
              "icon": "lucide-file",
              "title": "Jala_University-Engenharia_de_Software"
            }
          },
          {
            "id": "05f34e199d7594c9",
            "type": "leaf",
            "state": {
              "type": "markdown",
              "state": {
                "file": "Jala_University-Semestre_1.md",
                "mode": "source",
                "source": true
              },
              "icon": "lucide-file",
              "title": "Jala_University-Semestre_1"
            }
          },
          {
            "id": "d2393774b6eac307",
            "type": "leaf",
            "state": {
              "type": "markdown",
              "state": {
                "file": "Jala_University-Logica.md",
                "mode": "preview",
                "source": true
              },
              "icon": "lucide-file",
              "title": "Jala_University-Logica"
            }
          }
        ]
      }
    ],
    "direction": "vertical"
  },
  "left": {
    "id": "a2e13bdf10c8acda",
    "type": "split",
    "children": [
      {
        "id": "30bd28f47e4c0232",
        "type": "tabs",
        "dimension": 59.36599423631124,
        "children": [
          {
            "id": "8afc08e9adc94d60",
            "type": "leaf",
            "state": {
              "type": "file-explorer",
              "state": {
                "sortOrder": "alphabetical",
                "autoReveal": false
              },
              "icon": "lucide-folder-closed",
              "title": "Files"
            }
          },
          {
            "id": "0709b5acb3be86a0",
            "type": "leaf",
            "state": {
              "type": "search",
              "state": {
                "query": "",
                "matchingCase": false,
                "explainSearch": false,
                "collapseAll": false,
                "extraContext": false,
                "sortOrder": "alphabetical"
              },
              "icon": "lucide-search",
              "title": "Search"
            }
          },
          {
            "id": "2849009a06d1bf3b",
            "type": "leaf",
            "state": {
              "type": "bookmarks",
              "state": {},
              "icon": "lucide-bookmark",
              "title": "Bookmarks"
            }
          }
        ]
      },
      {
        "id": "be797bd30093f53a",
        "type": "tabs",
        "dimension": 40.63400576368876,
        "children": [
          {
            "id": "0d7467c555362e50",
            "type": "leaf",
            "state": {
              "type": "localgraph",
              "state": {
                "file": "content/notas/2025/05/07/entrada/Jala_University-Engenharia_de_Software.md",
                "options": {
                  "collapse-filter": true,
                  "search": "",
                  "localJumps": 1,
                  "localBacklinks": true,
                  "localForelinks": true,
                  "localInterlinks": false,
                  "showTags": false,
                  "showAttachments": false,
                  "hideUnresolved": false,
                  "collapse-color-groups": true,
                  "colorGroups": [],
                  "collapse-display": false,
                  "showArrow": false,
                  "textFadeMultiplier": -2.9,
                  "nodeSizeMultiplier": 1,
                  "lineSizeMultiplier": 1,
                  "collapse-forces": true,
                  "centerStrength": 0.518713248970312,
                  "repelStrength": 10,
                  "linkStrength": 1,
                  "linkDistance": 250,
                  "scale": 0.2962962962962963,
                  "close": true
                }
              },
              "icon": "lucide-git-fork",
              "title": "Graph of Jala_University-Engenharia_de_Software"
            }
          }
        ]
      }
    ],
    "direction": "horizontal",
    "width": 317.5
  },
  "right": {
    "id": "70366b6089a4156a",
    "type": "split",
    "children": [
      {
        "id": "6b50f908680f7f45",
        "type": "tabs",
        "children": [
          {
            "id": "206c822907d055d5",
            "type": "leaf",
            "state": {
              "type": "backlink",
              "state": {
                "file": "content/notas/2024/07/26/atomo/SSH.md",
                "collapseAll": true,
                "extraContext": true,
                "sortOrder": "alphabetical",
                "showSearch": false,
                "searchQuery": "",
                "backlinkCollapsed": false,
                "unlinkedCollapsed": false
              },
              "icon": "links-coming-in",
              "title": "Backlinks for SSH"
            }
          },
          {
            "id": "e465a5e07162d43d",
            "type": "leaf",
            "state": {
              "type": "outgoing-link",
              "state": {
                "file": "content/notas/2024/07/26/atomo/Xadrez_Abertura_Amar.md",
                "linksCollapsed": false,
                "unlinkedCollapsed": true
              },
              "icon": "links-going-out",
              "title": "Outgoing links from Xadrez_Abertura_Amar"
            }
          },
          {
            "id": "b966d9b9fff20eff",
            "type": "leaf",
            "state": {
              "type": "tag",
              "state": {
                "sortOrder": "frequency",
                "useHierarchy": true,
                "showSearch": false,
                "searchQuery": ""
              },
              "icon": "lucide-tags",
              "title": "Tags"
            }
          },
          {
            "id": "7fc3b17856a6aa5a",
            "type": "leaf",
            "state": {
              "type": "outline",
              "state": {
                "file": "content/notas/2024/09/08/atomo/apoie.md",
                "followCursor": false,
                "showSearch": false,
                "searchQuery": ""
              },
              "icon": "lucide-list",
              "title": "Outline of apoie"
            }
          }
        ]
      }
    ],
    "direction": "horizontal",
    "width": 300,
    "collapsed": true
  },
  "left-ribbon": {
    "hiddenItems": {
      "switcher:Open quick switcher": false,
      "graph:Open graph view": false,
      "canvas:Create new canvas": false,
      "daily-notes:Open today's daily note": false,
      "templates:Insert template": false,
      "command-palette:Open command palette": false,
      "obsidian-excalidraw-plugin:New drawing": false,
      "obsidian-git:Open Git source control": false
    }
  },
  "active": "5195e31f07bf8a86",
  "lastOpenFiles": [
    "Jala_University-Semestre_1.md",
    "content/notas/2025/05/07/entrada/Jala_University-Engenharia_de_Software.md",
    "Jala_University-Logica.md",
    "Excalidraw/Jala-Engenharia_software-Curso_admissao-Regras.excalidraw.md",
    "content/notas/2025/06/10/entrada/Jala-Cognicao_e_metacognicao.md",
    "Metacognicao.md",
    "content/notas/2025/06/17/atomo/Cognicao.md",
    "content/notas/2025/06/10/atomo/Efeito_pigmaleao.md",
    "content/notas/2025/06/17/atomo",
    "content/notas/2025/06/17",
    "Reunião Jala.md",
    "content/notas/2025/06/10/atomo",
    "content/notas/2025/05/12/entrada/Jala University - Curso de admissão da Engenharia de Software.md",
    "content/notas/2025/05/07/entrada/Jala University.md",
    "content/notas/2025/03/31/entrada/Zorin OS.md",
    "content/notas/2025/03/31/atomo/streaming.md",
    "content/notas/2025/03/31/atomo/podcasts.md",
    "content/notas/2025/03/31/entrada",
    "content/notas/2025/03/30/entrada/The_Unattended.md",
    "content/notas/2025/03/30/entrada/Spotify.md",
    "content/notas/2025/03/31/atomo",
    "content/notas/2025/03/31",
    "content/assets/images/2025/Pasted image 20250512154405.png",
    "content/assets/images/2024/Pasted Image 20240613173345_877.png",
    "content/assets/images/2024/Pasted Image 20240613172503_261.png",
    "content/assets/images/2025/Pasted image 20250507015436.png",
    "content/assets/images/2025",
    "content/notas/2025/05/12/entrada",
    "content/notas/2025/05/12",
    "content/notas/2025/05/07/entrada",
    "content/notas/2025/03/21/entrada/UNIX.md",
    "content/notas/2024/07/12/entrada/Obsidian_Sintaxe.md",
    "Pasted Image 20250507015520_828.png",
    "Pasted image 20250507015454.png",
    "Pasted image 20250507015500.png",
    "content/notas/2024/07/26/entrada/Toram_Status.md",
    "content/notas/2024/07/08/atomo/Markdown.md",
    "content/notas/2024/07/08/atomo/Memoria_de_longo_prazo.md",
    "content/notas/2024/07/12/atomo/Memoria_de_curto_prazo.md",
    "content/notas/2024/07/08/Entrada/Obsidian.md",
    "content/notas/2025/03/30/entrada/Krita.md",
    "content/notas/2024/07/26/atomo/SSH.md",
    "content/notas/2024/07/08/Entrada/ssh_agent.md",
    "Excalidraw/Jala-Engenharia_software-Curso_admissao-Regras.excalidraw.svg",
    "content/excalidraw/2024/07/trigrama_calculo.excalidraw.md.svg",
    "content/excalidraw/2024/07/Garyou_Tensei_Player.excalidraw.svg"
  ]
}